ghslc/__init__.py
ghslc/ghslc.py
ghslc-0.1.13.dist-info/LICENSE
ghslc-0.1.13.dist-info/METADATA
ghslc-0.1.13.dist-info/WHEEL
ghslc-0.1.13.dist-info/top_level.txt
ghslc-0.1.13.dist-info/RECORD
