Metadata-Version: 2.1
Name: ghslc
Version: 0.1.13
Summary: GHSL Land Cover python module
Home-page: https://github.com/ec-jrc/GHS-LC-SERV
Author: Luca Maffenini
Author-email: jrc-ghsl-tools@ec.europa.eu
License: GPLv3
Classifier: Environment :: Console
Classifier: Intended Audience :: Science/Research
Classifier: License :: OSI Approved :: GNU General Public License v3 (GPLv3)
Classifier: Programming Language :: Python :: 3
Classifier: Topic :: Scientific/Engineering :: GIS
Classifier: Topic :: Scientific/Engineering :: Image Processing
Requires-Python: >=3.7
License-File: LICENSE
Requires-Dist: PyYAML
Requires-Dist: rasterio
Requires-Dist: GDAL
Requires-Dist: numpy
Requires-Dist: pillow
Requires-Dist: scipy
Requires-Dist: scikit-image
